{
  "app_name": "compliance",
  "src_hash": "921cc8958e2d706e9193e256aa73abb1935f571b",
  "src_tag": "",
  "src_branch": "master",
  "patternfly_dependencies": ["@patternfly/patternfly@4.65.6","@patternfly/react-charts@6.12.2","@patternfly/react-core@4.79.2","@patternfly/react-icons@4.7.18","@patternfly/react-table@4.19.24","@patternfly/react-tokens@4.9.18"],
  "travis": {
    "event_type": "push",
    "build_number": "5388",
    "build_web_url": "https://travis-ci.com/RedHatInsights/compliance-frontend/builds/210090874"
  }
}
